util_moderngl_qt/Colormap.py
util_moderngl_qt/DrawerCylinders.py
util_moderngl_qt/DrawerDepthProjection.py
util_moderngl_qt/DrawerMesh.py
util_moderngl_qt/DrawerMeshColorMap.py
util_moderngl_qt/DrawerMeshNormal.py
util_moderngl_qt/DrawerMeshTexture.py
util_moderngl_qt/DrawerMeshUnindex.py
util_moderngl_qt/DrawerMeshVtxColor.py
util_moderngl_qt/DrawerSpheres.py
util_moderngl_qt/DrawerViewBoundary.py
util_moderngl_qt/OfflineRenderer.py
util_moderngl_qt/QGLWidgetViewer3.py
util_moderngl_qt/QGLWidgetViewer3Texture.py
util_moderngl_qt/__init__.py
util_moderngl_qt/primitive_shapes.py
util_moderngl_qt/view_navigation3.py
util_moderngl_qt-0.1.21.dist-info/METADATA
util_moderngl_qt-0.1.21.dist-info/WHEEL
util_moderngl_qt-0.1.21.dist-info/top_level.txt
util_moderngl_qt-0.1.21.dist-info/RECORD
