Metadata-Version: 2.1
Name: util-moderngl-qt
Version: 0.1.21
Requires-Dist: moderngl
Requires-Dist: numpy
Requires-Dist: pyrr
Requires-Dist: pyqt5
